chocolatey/__about__.py
chocolatey/__init__.py
chocolatey/_chocolatey.py
chocolatey/_chocolatey_cmd.py
chocolatey/py.typed
chocolatey/choco-setup/7za.exe.dsc.txt
chocolatey/choco-setup/chocolatey.2.5.1.nupkg
chocolatey/choco-setup/chocolatey.2.5.1.nupkg.dsc.txt
chocolatey/choco-setup/install.ps1
chocolatey/choco-setup/install.ps1.dsc.txt
chocolatey/exe-bin/elevator.exe
chocolatey/exe-bin/launcher.exe
py_chocolatey-0.9.0.dist-info/licenses/LICENSE
py_chocolatey-0.9.0.dist-info/METADATA
py_chocolatey-0.9.0.dist-info/WHEEL
py_chocolatey-0.9.0.dist-info/top_level.txt
py_chocolatey-0.9.0.dist-info/zip-safe
py_chocolatey-0.9.0.dist-info/RECORD
