Metadata-Version: 2.4
Name: py-chocolatey
Version: 0.9.0
Summary: API for Chocolatey, the Package Manager for Windows.
Author: Adam Karpierz
Author-email: adam@karpierz.net
Maintainer: Adam Karpierz
Maintainer-email: adam@karpierz.net
License-Expression: Zlib
Project-URL: Homepage, https://pypi.org/project/py-chocolatey/
Project-URL: Documentation, https://py-chocolatey.readthedocs.io/
Project-URL: Download, https://pypi.org/project/py-chocolatey/
Project-URL: Source, https://github.com/karpierz/py-chocolatey
Project-URL: Issues, https://github.com/karpierz/py-chocolatey/issues
Keywords: chocolatey,choco
Platform: win32
Classifier: Development Status :: 5 - Production/Stable
Classifier: Intended Audience :: Developers
Classifier: Operating System :: Microsoft :: Windows
Classifier: Natural Language :: Polish
Classifier: Programming Language :: Python
Classifier: Programming Language :: Python :: 3
Classifier: Programming Language :: Python :: 3.10
Classifier: Programming Language :: Python :: 3.11
Classifier: Programming Language :: Python :: 3.12
Classifier: Programming Language :: Python :: 3.13
Classifier: Programming Language :: Python :: 3.14
Classifier: Programming Language :: Python :: 3 :: Only
Classifier: Programming Language :: Python :: Implementation :: CPython
Classifier: Programming Language :: Python :: Implementation :: PyPy
Classifier: Topic :: Software Development :: Libraries :: Python Modules
Classifier: Typing :: Typed
Requires-Python: <4.0.0,>=3.10.0
License-File: LICENSE
Requires-Dist: setuptools>=80.9.0
Requires-Dist: typing_extensions>=4.15.0
Requires-Dist: pkg-about>=2.0.0
Requires-Dist: py-utlx>=1.1.0
Requires-Dist: nocasedict>=2.1.0
Requires-Dist: regex>=2025.9.18
Requires-Dist: platformdirs>=4.4.0
Provides-Extra: doc
Requires-Dist: Sphinx>=8.1.3; extra == "doc"
Requires-Dist: sphinx-autodoc-typehints>=3.0.1; extra == "doc"
Requires-Dist: sphinx-toolbox>=4.0.0; extra == "doc"
Requires-Dist: sphinx-tabs>=3.4.5; extra == "doc"
Requires-Dist: sphinx-copybutton>=0.5.2; extra == "doc"
Requires-Dist: sphinxcontrib-spelling>=8.0.1; extra == "doc"
Requires-Dist: sphinx-lint>=1.0.0; extra == "doc"
Requires-Dist: restructuredtext-lint>=1.4.0; extra == "doc"
Requires-Dist: nbsphinx>=0.9.7; extra == "doc"
Provides-Extra: test
Requires-Dist: deepdiff>=8.6.1; extra == "test"
Requires-Dist: rich>=14.1.0; extra == "test"
Dynamic: license-file
